picker/__init__.py
picker/__main__.py
picker/abstractionhelper.py
picker/action.py
picker/argument_parsing.py
picker/emoji_data.py
picker/file_loader.py
picker/frecent.py
picker/mode.py
picker/models.py
picker/paths.py
picker/recent.py
picker/standalone.py
picker/clipboarder/__init__.py
picker/clipboarder/clipboarder.py
picker/clipboarder/noop.py
picker/clipboarder/pbcopy.py
picker/clipboarder/wl.py
picker/clipboarder/xclip.py
picker/clipboarder/xsel.py
picker/contrib/grid-icons-only.rasi
picker/contrib/grid.rasi
picker/data/adlam.csv
picker/data/aegean_numbers.csv
picker/data/ahom.csv
picker/data/alchemical_symbols.csv
picker/data/alphabetic_presentation_forms.csv
picker/data/anatolian_hieroglyphs.csv
picker/data/ancient_greek_musical_notation.csv
picker/data/ancient_greek_numbers.csv
picker/data/ancient_symbols.csv
picker/data/arabic.csv
picker/data/arabic_extended-a.csv
picker/data/arabic_extended-b.csv
picker/data/arabic_extended-c.csv
picker/data/arabic_mathematical_alphabetic_symbols.csv
picker/data/arabic_presentation_forms-a.csv
picker/data/arabic_presentation_forms-b.csv
picker/data/arabic_supplement.csv
picker/data/armenian.csv
picker/data/arrows.csv
picker/data/avestan.csv
picker/data/balinese.csv
picker/data/bamum.csv
picker/data/bamum_supplement.csv
picker/data/basic_latin.csv
picker/data/bassa_vah.csv
picker/data/batak.csv
picker/data/bengali.csv
picker/data/beria_erfe.csv
picker/data/bhaiksuki.csv
picker/data/block_elements.csv
picker/data/bopomofo.csv
picker/data/bopomofo_extended.csv
picker/data/box_drawing.csv
picker/data/brahmi.csv
picker/data/braille_patterns.csv
picker/data/buginese.csv
picker/data/buhid.csv
picker/data/byzantine_musical_symbols.csv
picker/data/carian.csv
picker/data/caucasian_albanian.csv
picker/data/chakma.csv
picker/data/cham.csv
picker/data/cherokee.csv
picker/data/cherokee_supplement.csv
picker/data/chess_symbols.csv
picker/data/chorasmian.csv
picker/data/cjk_cantonese.csv
picker/data/cjk_compatibility.csv
rofimoji-6.7.0.dist-info/METADATA
rofimoji-6.7.0.dist-info/WHEEL
rofimoji-6.7.0.dist-info/entry_points.txt
rofimoji-6.7.0.dist-info/licenses/LICENSE
rofimoji-6.7.0.dist-info/RECORD
