Metadata-Version: 2.4
Name: rofimoji
Version: 6.7.0
Summary: Simple character picker using rofi
Project-URL: homepage, https://github.com/fdw/rofimoji
Project-URL: repository, https://github.com/fdw/rofimoji
Author-email: Fabian Winter <5821180+fdw@users.noreply.github.com>
License: MIT
License-File: LICENSE
Requires-Python: >=3.9
Requires-Dist: configargparse<2.0,>=1.3
